reader/__init__.py
reader/__main__.py
reader/config.txt
reader/feed.py
reader/viewer.py
sumit_reader-1.0.0.dist-info/METADATA
sumit_reader-1.0.0.dist-info/WHEEL
sumit_reader-1.0.0.dist-info/entry_points.txt
sumit_reader-1.0.0.dist-info/top_level.txt
sumit_reader-1.0.0.dist-info/RECORD
