Metadata-Version: 2.1
Name: sumit-reader
Version: 1.0.0
Summary: Read the latest Real Python tutorials
Home-page: https://github.com/Ammyy9908/sumit-reader
Author: Real Python
Author-email: sb78639@gmail.com
License: MIT
Platform: UNKNOWN
Classifier: License :: OSI Approved :: MIT License
Classifier: Programming Language :: Python :: 3
Classifier: Programming Language :: Python :: 3.7
Requires-Dist: feedparser
Requires-Dist: html2text
